src/robotcode/plugin/__init__.py
src/robotcode/plugin/__version__.py
src/robotcode/plugin/manager.py
src/robotcode/plugin/py.typed
src/robotcode/plugin/specs.py
src/robotcode/plugin/click_helper/aliases.py
src/robotcode/plugin/click_helper/options.py
src/robotcode/plugin/click_helper/types.py
robotcode_plugin-2.0.0.dist-info/METADATA
robotcode_plugin-2.0.0.dist-info/WHEEL
robotcode_plugin-2.0.0.dist-info/RECORD
