Metadata-Version: 2.4
Name: robotcode-plugin
Version: 2.0.0
Summary: Some classes for RobotCode plugin management
Project-URL: Donate, https://opencollective.com/robotcode
Project-URL: Documentation, https://github.com/robotcodedev/robotcode#readme
Project-URL: Changelog, https://github.com/robotcodedev/robotcode/blob/main/CHANGELOG.md
Project-URL: Issues, https://github.com/robotcodedev/robotcode/issues
Project-URL: Source, https://github.com/robotcodedev/robotcode
Author-email: Daniel Biehl <dbiehl@live.de>
License: Apache-2.0
Classifier: Development Status :: 5 - Production/Stable
Classifier: Framework :: Robot Framework
Classifier: Framework :: Robot Framework :: Tool
Classifier: Operating System :: OS Independent
Classifier: Programming Language :: Python
Classifier: Programming Language :: Python :: 3.10
Classifier: Programming Language :: Python :: 3.11
Classifier: Programming Language :: Python :: 3.12
Classifier: Programming Language :: Python :: 3.13
Classifier: Programming Language :: Python :: 3.14
Classifier: Programming Language :: Python :: Implementation :: CPython
Classifier: Programming Language :: Python :: Implementation :: PyPy
Classifier: Topic :: Utilities
Classifier: Typing :: Typed
Requires-Python: >=3.10
Requires-Dist: click>=8.1.0
Requires-Dist: colorama>=0.4.6
Requires-Dist: pluggy>=1.0.0
Requires-Dist: tomli-w>=1.0.0
